{
  "title": "AD #8 · Environmental Tax on Flights",
  "rounds": [
    {
      "name": "Round 1 · 连接词",
      "description": "转折 / 并列 / 因果 / 对比 / 让步 / 总结",
      "tokens": [
        { "t": "text", "v": "A tax on plane tickets sounds like a clean idea — polluters pay, green technology gets funded — " },
        { "t": "blank", "answer": "but", "hint": "b" },
        { "t": "text", "v": " whether it actually helps depends fully on how the tax is designed. I would support it only in a narrow form: place it on short routes where trains are already an option, " },
        { "t": "blank", "answer": "and", "hint": "a" },
        { "t": "text", "v": " require by law that the money goes into cleaner transport. A flat tax on every ticket would miss the target on all three fronts.\n" },
        { "t": "blank", "answer": "First,", "hint": "F" },
        { "t": "text", "v": " the plan only works " },
        { "t": "blank", "answer": "where", "hint": "w" },
        { "t": "text", "v": " passengers can switch. On routes like Paris–Lyon, a small extra fee pushes travelers onto high-speed rail " },
        { "t": "blank", "answer": "and", "hint": "a" },
        { "t": "text", "v": " real emissions drop. On long-haul flights, " },
        { "t": "blank", "answer": "where", "hint": "w" },
        { "t": "text", "v": " no train exists, the same tax just becomes a fixed cost. The flight still takes off, " },
        { "t": "blank", "answer": "and", "hint": "a" },
        { "t": "text", "v": " the bill falls on economy passengers " },
        { "t": "blank", "answer": "while", "hint": "w" },
        { "t": "text", "v": " business travelers feel nothing.\n" },
        { "t": "blank", "answer": "Second,", "hint": "S" },
        { "t": "text", "v": " the scale is too small. Flying makes up only about 2.5% of global carbon; forcing airlines to use cleaner fuel " },
        { "t": "blank", "answer": "or", "hint": "o" },
        { "t": "text", "v": " join a wider carbon-trading system would cover far more ground.\n" },
        { "t": "blank", "answer": "Third,", "hint": "T" },
        { "t": "text", "v": " in several European trials, green-tax money was quietly moved into the general budget. " },
        { "t": "blank", "answer": "Without", "hint": "W" },
        { "t": "text", "v": " legal rules locking the money to green use, this is a revenue plan with a green label." }
      ]
    },
    {
      "name": "Round 2 · 动词搭配",
      "description": "动词或动词短语",
      "tokens": [
        { "t": "text", "v": "A tax on plane tickets " },
        { "t": "blank", "answer": "sounds", "hint": "s" },
        { "t": "text", "v": " like a clean idea — polluters " },
        { "t": "blank", "answer": "pay,", "hint": "p" },
        { "t": "text", "v": " green technology " },
        { "t": "blank", "answer": "gets", "hint": "g" },
        { "t": "text", "v": " funded — but whether it actually " },
        { "t": "blank", "answer": "helps", "hint": "h" },
        { "t": "text", "v": " depends fully on how the tax is designed. I would " },
        { "t": "blank", "answer": "support", "hint": "s" },
        { "t": "text", "v": " it only in a narrow form. A flat tax would " },
        { "t": "blank", "answer": "miss", "hint": "m" },
        { "t": "text", "v": " the target. The plan only " },
        { "t": "blank", "answer": "works", "hint": "w" },
        { "t": "text", "v": " where passengers can " },
        { "t": "blank", "answer": "switch.", "hint": "s" },
        { "t": "text", "v": " A small extra fee " },
        { "t": "blank", "answer": "pushes", "hint": "p" },
        { "t": "text", "v": " travelers onto high-speed rail and real emissions " },
        { "t": "blank", "answer": "drop.", "hint": "d" },
        { "t": "text", "v": " The flight still " },
        { "t": "blank", "answer": "takes", "hint": "t" },
        { "t": "text", "v": " off, and the bill " },
        { "t": "blank", "answer": "falls", "hint": "f" },
        { "t": "text", "v": " on economy passengers. Forcing airlines to " },
        { "t": "blank", "answer": "use", "hint": "u" },
        { "t": "text", "v": " cleaner fuel would " },
        { "t": "blank", "answer": "cover", "hint": "c" },
        { "t": "text", "v": " far more ground. Green-tax money was quietly " },
        { "t": "blank", "answer": "moved", "hint": "m" },
        { "t": "text", "v": " into the general budget." }
      ]
    },
    {
      "name": "Round 3 · 名词短语",
      "description": "核心概念名词或「形容词＋名词」搭配",
      "tokens": [
        { "t": "text", "v": "A " },
        { "t": "blank", "answer": "tax", "hint": "t" },
        { "t": "text", "v": " on plane " },
        { "t": "blank", "answer": "tickets", "hint": "t" },
        { "t": "text", "v": " sounds like a clean " },
        { "t": "blank", "answer": "idea", "hint": "i" },
        { "t": "text", "v": " — polluters pay, green " },
        { "t": "blank", "answer": "technology", "hint": "t" },
        { "t": "text", "v": " gets funded. I would support it only in a narrow " },
        { "t": "blank", "answer": "form:", "hint": "f" },
        { "t": "text", "v": " place it on short " },
        { "t": "blank", "answer": "routes", "hint": "r" },
        { "t": "text", "v": " where trains are already an option. A flat tax on every ticket would miss the " },
        { "t": "blank", "answer": "target", "hint": "t" },
        { "t": "text", "v": " on all three " },
        { "t": "blank", "answer": "fronts.", "hint": "f" },
        { "t": "text", "v": " A small extra " },
        { "t": "blank", "answer": "fee", "hint": "f" },
        { "t": "text", "v": " pushes travelers onto " },
        { "t": "blank", "answer": "high-speed", "hint": "h" },
        { "t": "text", "v": " " },
        { "t": "blank", "answer": "rail", "hint": "r" },
        { "t": "text", "v": " and real " },
        { "t": "blank", "answer": "emissions", "hint": "e" },
        { "t": "text", "v": " drop. The bill falls on economy " },
        { "t": "blank", "answer": "passengers", "hint": "p" },
        { "t": "text", "v": " while business " },
        { "t": "blank", "answer": "travelers", "hint": "t" },
        { "t": "text", "v": " feel nothing. Flying makes up only about 2.5% of global " },
        { "t": "blank", "answer": "carbon;", "hint": "c" },
        { "t": "text", "v": " forcing airlines to use cleaner " },
        { "t": "blank", "answer": "fuel", "hint": "f" },
        { "t": "text", "v": " or join a wider " },
        { "t": "blank", "answer": "carbon-trading", "hint": "c" },
        { "t": "text", "v": " " },
        { "t": "blank", "answer": "system", "hint": "s" },
        { "t": "text", "v": " would cover far more " },
        { "t": "blank", "answer": "ground.", "hint": "g" }
      ]
    },
    {
      "name": "Round 4 · 句法骨架",
      "description": "整块从句 / 介词短语 / 修饰结构",
      "tokens": [
        { "t": "text", "v": "A tax on plane tickets sounds like a clean idea — polluters pay, green technology gets funded — but " },
        { "t": "blank", "answer": "whether it actually helps depends fully on how the tax is designed.", "hint": "w" },
        { "t": "text", "v": " I would support it only in a narrow form: " },
        { "t": "blank", "answer": "place it on short routes where trains are already an option,", "hint": "p" },
        { "t": "text", "v": " and require by law that the money goes into cleaner transport.\nFirst, the plan only works " },
        { "t": "blank", "answer": "where passengers can switch.", "hint": "w" },
        { "t": "text", "v": " On routes like Paris–Lyon or Beijing–Tianjin, a small extra fee pushes travelers onto high-speed rail and real emissions drop. On long-haul flights, " },
        { "t": "blank", "answer": "where no train exists,", "hint": "w" },
        { "t": "text", "v": " the same tax just becomes a fixed cost. The flight still takes off, and the bill falls on economy passengers " },
        { "t": "blank", "answer": "while business travelers, whose tickets are paid by the company, feel nothing.", "hint": "w" },
        { "t": "text", "v": "\nSecond, the scale is too small. Flying makes up only about 2.5% of global carbon; " },
        { "t": "blank", "answer": "forcing airlines to use cleaner fuel or join a wider carbon-trading system", "hint": "f" },
        { "t": "text", "v": " would cover far more ground.\nThird, in several European trials, green-tax money was quietly moved into the general budget. " },
        { "t": "blank", "answer": "Without legal rules locking the money to green use,", "hint": "W" },
        { "t": "text", "v": " this is a revenue plan with a green label." }
      ]
    }
  ]
}
